autostatic.py
pelican_autostatic-1.0.0.dist-info/LICENSE
pelican_autostatic-1.0.0.dist-info/METADATA
pelican_autostatic-1.0.0.dist-info/WHEEL
pelican_autostatic-1.0.0.dist-info/top_level.txt
pelican_autostatic-1.0.0.dist-info/RECORD
