Metadata-Version: 2.1
Name: pelican-autostatic
Version: 1.0.0
Summary: A generator for Pelican allowing flexible referencing of static content
Home-page: https://github.com/AlexJF/pelican-autostatic
Download-URL: https://github.com/AlexJF/pelican-autostatic/archive/v0.2.2.zip
Author: Alexandre Fonseca
Author-email: alexandrejorgefonseca@gmail.com
License: Apache
Keywords: pelican blog static generic automatic
Platform: UNKNOWN
License-File: LICENSE
Requires-Dist: pelican (>=3.4.0)
